LICENSE
MANIFEST.in
README.md
pyproject.toml
setup.py
src/clusterondemandaws/__init__.py
src/clusterondemandaws/awsconnection.py
src/clusterondemandaws/base.py
src/clusterondemandaws/brightsetup.py
src/clusterondemandaws/cli.py
src/clusterondemandaws/clientutils.py
src/clusterondemandaws/cluster.py
src/clusterondemandaws/clustercreate.py
src/clusterondemandaws/clusterdelete.py
src/clusterondemandaws/clusterlist.py
src/clusterondemandaws/clusterstart.py
src/clusterondemandaws/clusterstop.py
src/clusterondemandaws/configdump.py
src/clusterondemandaws/configshow.py
src/clusterondemandaws/configuration.py
src/clusterondemandaws/efs.py
src/clusterondemandaws/imagelist.py
src/clusterondemandaws/images.py
src/clusterondemandaws/instancetype.py
src/clusterondemandaws/instancetypelist.py
src/clusterondemandaws/paramvalidation.py
src/clusterondemandaws/summary.py
src/clusterondemandaws/vpc.py
src/cm_cluster_on_demand_aws.egg-info/PKG-INFO
src/cm_cluster_on_demand_aws.egg-info/SOURCES.txt
src/cm_cluster_on_demand_aws.egg-info/dependency_links.txt
src/cm_cluster_on_demand_aws.egg-info/entry_points.txt
src/cm_cluster_on_demand_aws.egg-info/requires.txt
src/cm_cluster_on_demand_aws.egg-info/top_level.txt